<?xml version="1.0" encoding="utf-8"?>
<layer-list
  xmlns:android="http://schemas.android.com/apk/res/android">
    <item android:gravity="center">
        <shape android:shape="rectangle">
            <size android:height="37.0dip" android:width="37.0dip" />
			<corners android:topLeftRadius="90.0dp" android:topRightRadius="90.0dp" android:bottomLeftRadius="90.0dp" android:bottomRightRadius="24.0dp"/>
            <gradient android:startColor="@*android:color/accent_material_dark" android:endColor="@*android:color/accent_material_light" android:angle="90.0" />
        </shape>
    </item>
    <item android:gravity="center">
        <shape android:shape="rectangle">
            <size android:height="34.0dip" android:width="34.0dip" />
			<corners android:topLeftRadius="90.0dp" android:topRightRadius="90.0dp" android:bottomLeftRadius="90.0dp" android:bottomRightRadius="24.0dp"/>
            <gradient android:startColor="@*android:color/transparent" android:endColor="@*android:color/group_button_dialog_pressed_holo_dark" android:angle="90.0" />
        </shape>
    </item>
    <item>
        <vector android:height="24.0dip" android:width="24.0dip" android:viewportWidth="24.0" android:viewportHeight="24.0">
            <group android:pivotX="24.0" android:pivotY="24.0" android:scaleX="1.0" android:scaleY="1.0">
                <path android:fillColor="@*android:color/white" android:pathData="M10.1999,13.4308V7.3846H11.0307V16.5915L8.5654,13.4308H10.1999Z" android:fillType="evenOdd" />
                <path android:fillColor="@*android:color/white" android:pathData="M12.9692,7.4085L15.4344,10.5692H13.8V16.6154H12.9692V7.4085Z" android:fillType="evenOdd" />
            </group>
        </vector>
    </item>
</layer-list>