<?xml version="1.0" encoding="utf-8"?>
<resources>
    <color name="system_accent1_600">#1cff12</color>
    <color name="accent_material_light">#1cff12</color>
    <color name="accent_material_dark">#1cff12</color>
    <color name="keyguard_avatar_frame_pressed_color">#401cff12</color>
    <color name="holo_red_light">#cc1cff12</color>
    <color name="highlighted_text_dark">#991cff12</color>
    <color name="highlighted_text_light">#991cff12</color>
    <color name="accessibility_focus_highlight_color">#bf1cff12</color>
    <color name="holo_button_normal">#211cff12</color>
    <color name="ripple_material_dark">#801cff12</color>
    <color name="ripple_material_light">#661cff12</color>
    <color name="holo_blue_light">#00c500</color>
</resources>